de_utils/__init__.py
de_utils/_de_utils_exception.py
de_utils/_logging_utils.py
de_utils/_utils.py
de_utils/_version.py
de_utils/catalog_utils/__init__.py
de_utils/catalog_utils/_catalog_utils.py
de_utils/engineering_utils/__init__.py
de_utils/engineering_utils/_csv_loader.py
de_utils/engineering_utils/_excel_mapper.py
de_utils/engineering_utils/_fwf_loader.py
de_utils/engineering_utils/_fwf_schema_manager.py
de_utils/engineering_utils/_schema_manager.py
de_utils/engineering_utils/_table_loader.py
de_utils/engineering_utils/common_test_data.py
de_utils/hdfs_utils/__init__.py
de_utils/hdfs_utils/_filename_handler.py
de_utils/hdfs_utils/_filter_files_by_date.py
de_utils/hdfs_utils/_hdfs_utils.py
de_utils/hdfs_utils/_hdfs_utils_exception.py
de_utils/hdfs_utils/_manifest.py
de_utils/lookups/__init__.py
de_utils/lookups/_lookups.py
de_utils/spark_utils/__init__.py
de_utils/spark_utils/_column_utils.py
de_utils/spark_utils/_nspl.py
de_utils/spark_utils/_spark_utils.py
de_utils/spark_utils/_standardisation.py
de_utils/spark_utils/_validation.py
de_utils/test_data_generation/README.md
de_utils/test_data_generation/__init__.py
de_utils/test_data_generation/columns/__init__.py
de_utils/test_data_generation/columns/base_columns.py
de_utils/test_data_generation/columns/date_column.py
de_utils/test_data_generation/columns/decimal_column.py
de_utils/test_data_generation/columns/numeric_columns.py
de_utils/test_data_generation/columns/string_column.py
de_utils/test_data_generation/columns/timestamp_column.py
de_utils/test_data_generation/common.py
de_utils/test_data_generation/table_generator.py
data_eng_utils-0.11.1.dist-info/METADATA
data_eng_utils-0.11.1.dist-info/WHEEL
data_eng_utils-0.11.1.dist-info/RECORD
