Metadata-Version: 2.1
Name: data-eng-utils
Version: 0.11.1
Summary: de_utils is a package that contains collections of useful functions grouped by theme e.g. HDFS, Spark, Python, etc... and a data engineering framework under the engineering_utils sub-package.
Author: Office for National Statistics - Data Engineering
Requires-Python: >=3.6.8,<4
Classifier: Programming Language :: Python :: 3
Classifier: Programming Language :: Python :: 3.7
Classifier: Programming Language :: Python :: 3.8
Classifier: Programming Language :: Python :: 3.9
Classifier: Programming Language :: Python :: 3.10
Classifier: Programming Language :: Python :: 3.11
Requires-Dist: faker (==14.2.1)
Requires-Dist: openpyxl (>=3.1.2,<4.0.0)
Requires-Dist: pandas (==1.1.5)
Requires-Dist: pyspark (>=2.4.0)
Requires-Dist: tqdm (==4.64.0)
Requires-Dist: xlrd (>=2.0.1,<3.0.0)
